{
  "tag": "2023-07-20_052508",
  "state_str": "c3cd86f371dd59e0244fad93a7c768f8",
  "state_str_content_free": "ed2b0d0e0d196b0cf83da2ac6e06bc74",
  "foreground_activity": "appinventor.ai_care_medisyshealthcare.Medisys/.Screen1",
  "activity_stack": [
    "appinventor.ai_care_medisyshealthcare.Medisys/.Screen1"
  ],
  "background_services": [
    "com.google.android.apps.messaging/com.google.android.ims.service.JibeService",
    "com.google.android.networkstack.tethering/com.android.networkstack.tethering.TetheringService",
    "com.google.android.ext.services/com.android.textclassifier.DefaultTextClassifierService",
    "com.google.android.gms/.nearby.sharing.ReceiveSurfaceService",
    "com.google.android.apps.photos/androidx.work.impl.background.systemjob.SystemJobService",
    "com.google.android.gms/.deviceconnection.service.DeviceConnectionWatcherService",
    "com.android.systemui/.keyguard.KeyguardService",
    "com.android.chrome/org.chromium.content.app.SandboxedProcessService0",
    "com.android.chrome/org.chromium.content.app.SandboxedProcessService0",
    "com.android.chrome/org.chromium.content.app.SandboxedProcessService0",
    "com.android.bluetooth/.btservice.AdapterService",
    "com.android.systemui/.ImageWallpaper",
    "com.google.android.gms/.auth.setup.devicesignals.LockScreenService",
    "com.google.android.gms/.gcm.GcmService",
    "com.google.android.gms/.clearcut.debug.ClearcutDebugDumpService",
    "com.google.android.apps.messaging/com.google.android.ims.binding.SystemBindingService",
    "com.google.android.gms/.chimera.PersistentApiService",
    "com.google.android.gms/.location.geocode.GeocodeService",
    "com.android.phone/com.android.internal.telephony.CellularNetworkService",
    "com.google.android.gms/com.google.location.nearby.direct.service.NearbyDirectService",
    "com.google.android.gms/.chimera.PersistentBoundBrokerService",
    "com.android.bluetooth/.gatt.GattService",
    "com.google.android.gms/.fido.fido2.pollux.CableAuthenticatorService",
    "com.google.android.googlequicksearchbox/com.google.android.apps.gsa.nowoverlayservice.DrawerOverlayService",
    "io.github.ylimit.droidbotapp/.DroidBotIME",
    "com.android.bluetooth/.pbap.BluetoothPbapService",
    "com.google.android.gms/com.google.android.location.fused.FusedLocationService",
    "com.google.android.gms/.gcm.nts.SchedulerService",
    "com.google.android.ext.services/android.ext.services.autofill.InlineSuggestionRenderServiceImpl",
    "com.android.bluetooth/.a2dp.A2dpService",
    "com.google.android.providers.media.module/com.android.providers.media.fuse.ExternalStorageServiceImpl",
    "appinventor.ai_care_medisyshealthcare.Medisys/org.chromium.content.app.SandboxedProcessService0",
    "io.github.ylimit.droidbotapp/io.github.privacystreams.accessibility.PSAccessibilityService",
    "com.google.android.googlequicksearchbox/com.google.android.apps.gsa.nga.engine.viss.NgaService",
    "com.google.android.gms/.thunderbird.EmergencyPersistentService",
    "com.google.android.apps.nexuslauncher/com.android.launcher3.notification.NotificationListener",
    "com.android.systemui/.SystemUIService",
    "com.google.android.gms/.nearby.exposurenotification.service.ExposureMatchingService",
    "com.android.chrome/org.chromium.content.app.PrivilegedProcessService0",
    "android/.hardware.location.GeofenceHardwareService",
    "com.android.se/.SecureElementService",
    "com.google.android.gms/.chimera.PersistentDirectBootAwareApiService",
    "com.android.bluetooth/.hid.HidDeviceService",
    "com.google.android.gms/.geotimezone.GeoTimeZoneService",
    "com.google.android.gms/.location.persistent.LocationPersistentService",
    "com.google.android.gms/.nearby.discovery.service.DiscoveryService",
    "com.google.android.gms/com.google.android.location.internal.PendingIntentCallbackService",
    "com.google.android.gms/.nearby.messages.service.NearbyMessagesService",
    "com.google.android.gms/.fido.authenticator.service.AuthenticatorService",
    "com.google.android.gms/com.google.android.location.internal.server.GoogleLocationService",
    "com.google.android.gms/com.google.android.contextmanager.service.ContextManagerService",
    "com.android.systemui/.dump.SystemUIAuxiliaryDumpService",
    "com.google.android.gms/com.google.android.location.network.NetworkLocationService",
    "com.android.stk/.StkAppService",
    "com.google.android.gms/com.google.android.location.internal.GoogleLocationManagerService",
    "com.android.phone/com.android.internal.telephony.dataconnection.CellularDataService",
    "com.android.server.telecom/.components.TelecomService",
    "com.google.android.networkstack/com.android.server.NetworkStackService",
    "com.android.bluetooth/.hfp.HeadsetService",
    "com.google.android.googlequicksearchbox/com.google.android.voiceinteraction.GsaVoiceInteractionService",
    "com.android.phone/.vvm.RemoteVvmTaskManager",
    "com.android.ons/.OpportunisticNetworkService",
    "com.google.android.gms/.common.stats.GmsCoreStatsService",
    "com.google.android.gms/com.google.android.location.internal.server.HardwareArProviderService",
    "com.android.bluetooth/.map.BluetoothMapService",
    "com.android.phone/com.android.services.telephony.sip.components.TelephonySipService",
    "com.android.phone/.TelephonyDebugService",
    "com.android.bluetooth/.hid.HidHostService",
    "com.android.bluetooth/.opp.BluetoothOppService",
    "com.android.bluetooth/.pan.PanService",
    "com.android.bluetooth/.avrcp.AvrcpTargetService",
    "com.google.android.apps.nexuslauncher/com.android.quickstep.TouchInteractionService",
    "com.google.android.cellbroadcastservice/com.android.cellbroadcastservice.DefaultCellBroadcastService"
  ],
  "width": 1440,
  "height": 2560,
  "views": [
    {
      "package": "appinventor.ai_care_medisyshealthcare.Medisys",
      "visible": true,
      "checkable": false,
      "child_count": 1,
      "editable": false,
      "clickable": false,
      "is_password": false,
      "focusable": false,
      "enabled": true,
      "content_description": null,
      "children": [
        1
      ],
      "focused": false,
      "bounds": [
        [
          37,
          912
        ],
        [
          1403,
          1564
        ]
      ],
      "resource_id": null,
      "checked": false,
      "text": null,
      "class": "android.widget.FrameLayout",
      "scrollable": false,
      "selected": false,
      "long_clickable": false,
      "parent": -1,
      "temp_id": 0,
      "size": "1366*652",
      "signature": "[class]android.widget.FrameLayout[resource_id]None[text]None[enabled,,]",
      "view_str": "7f57d31ea182f7c075034b63f520cfb2",
      "content_free_signature": "[class]android.widget.FrameLayout[resource_id]None"
    },
    {
      "package": "appinventor.ai_care_medisyshealthcare.Medisys",
      "visible": true,
      "checkable": false,
      "child_count": 1,
      "editable": false,
      "clickable": false,
      "is_password": false,
      "focusable": false,
      "enabled": true,
      "content_description": null,
      "children": [
        2
      ],
      "focused": false,
      "bounds": [
        [
          93,
          968
        ],
        [
          1347,
          1508
        ]
      ],
      "resource_id": null,
      "checked": false,
      "text": null,
      "class": "android.widget.FrameLayout",
      "scrollable": false,
      "selected": false,
      "long_clickable": false,
      "parent": 0,
      "temp_id": 1,
      "size": "1254*540",
      "signature": "[class]android.widget.FrameLayout[resource_id]None[text]None[enabled,,]",
      "view_str": "e648260b867f8d6d6cb405245c67058c",
      "content_free_signature": "[class]android.widget.FrameLayout[resource_id]None"
    },
    {
      "package": "appinventor.ai_care_medisyshealthcare.Medisys",
      "visible": true,
      "checkable": false,
      "child_count": 1,
      "editable": false,
      "clickable": false,
      "is_password": false,
      "focusable": false,
      "enabled": true,
      "content_description": null,
      "children": [
        3
      ],
      "focused": false,
      "bounds": [
        [
          93,
          968
        ],
        [
          1347,
          1508
        ]
      ],
      "resource_id": "android:id/content",
      "checked": false,
      "text": null,
      "class": "android.widget.FrameLayout",
      "scrollable": false,
      "selected": false,
      "long_clickable": false,
      "parent": 1,
      "temp_id": 2,
      "size": "1254*540",
      "signature": "[class]android.widget.FrameLayout[resource_id]android:id/content[text]None[enabled,,]",
      "view_str": "fea0433d7744e7cd5528a94b97df4f50",
      "content_free_signature": "[class]android.widget.FrameLayout[resource_id]android:id/content"
    },
    {
      "package": "appinventor.ai_care_medisyshealthcare.Medisys",
      "visible": true,
      "checkable": false,
      "child_count": 3,
      "editable": false,
      "clickable": false,
      "is_password": false,
      "focusable": false,
      "enabled": true,
      "content_description": null,
      "children": [
        4,
        8,
        12
      ],
      "focused": false,
      "bounds": [
        [
          93,
          968
        ],
        [
          1347,
          1508
        ]
      ],
      "resource_id": "android:id/parentPanel",
      "checked": false,
      "text": null,
      "class": "android.widget.LinearLayout",
      "scrollable": false,
      "selected": false,
      "long_clickable": false,
      "parent": 2,
      "temp_id": 3,
      "size": "1254*540",
      "signature": "[class]android.widget.LinearLayout[resource_id]android:id/parentPanel[text]None[enabled,,]",
      "view_str": "f90caf875ce3a3140810a7030770f23b",
      "content_free_signature": "[class]android.widget.LinearLayout[resource_id]android:id/parentPanel"
    },
    {
      "package": "appinventor.ai_care_medisyshealthcare.Medisys",
      "visible": true,
      "checkable": false,
      "child_count": 2,
      "editable": false,
      "clickable": false,
      "is_password": false,
      "focusable": false,
      "enabled": true,
      "content_description": null,
      "children": [
        5,
        7
      ],
      "focused": false,
      "bounds": [
        [
          93,
          968
        ],
        [
          1347,
          1144
        ]
      ],
      "resource_id": "android:id/topPanel",
      "checked": false,
      "text": null,
      "class": "android.widget.LinearLayout",
      "scrollable": false,
      "selected": false,
      "long_clickable": false,
      "parent": 3,
      "temp_id": 4,
      "size": "1254*176",
      "signature": "[class]android.widget.LinearLayout[resource_id]android:id/topPanel[text]None[enabled,,]",
      "view_str": "2ce90a9efcbf24561b8a51bd53916846",
      "content_free_signature": "[class]android.widget.LinearLayout[resource_id]android:id/topPanel"
    },
    {
      "package": "appinventor.ai_care_medisyshealthcare.Medisys",
      "visible": true,
      "checkable": false,
      "child_count": 1,
      "editable": false,
      "clickable": false,
      "is_password": false,
      "focusable": false,
      "enabled": true,
      "content_description": null,
      "children": [
        6
      ],
      "focused": false,
      "bounds": [
        [
          93,
          968
        ],
        [
          1347,
          1116
        ]
      ],
      "resource_id": "android:id/title_template",
      "checked": false,
      "text": null,
      "class": "android.widget.LinearLayout",
      "scrollable": false,
      "selected": false,
      "long_clickable": false,
      "parent": 4,
      "temp_id": 5,
      "size": "1254*148",
      "signature": "[class]android.widget.LinearLayout[resource_id]android:id/title_template[text]None[enabled,,]",
      "view_str": "7ac9ef1a1a9ceabc44eb131b2dce8164",
      "content_free_signature": "[class]android.widget.LinearLayout[resource_id]android:id/title_template"
    },
    {
      "package": "appinventor.ai_care_medisyshealthcare.Medisys",
      "visible": true,
      "checkable": false,
      "child_count": 0,
      "editable": false,
      "clickable": false,
      "is_password": false,
      "focusable": false,
      "enabled": true,
      "content_description": null,
      "children": [],
      "focused": false,
      "bounds": [
        [
          177,
          1031
        ],
        [
          1263,
          1116
        ]
      ],
      "resource_id": "android:id/alertTitle",
      "checked": false,
      "text": "Are you sure you want to exit?",
      "class": "android.widget.TextView",
      "scrollable": false,
      "selected": false,
      "long_clickable": false,
      "parent": 5,
      "temp_id": 6,
      "size": "1086*85",
      "signature": "[class]android.widget.TextView[resource_id]android:id/alertTitle[text]Are you sure you want to exit?[enabled,,]",
      "view_str": "26d0e287daef7faebdf1be87dc097b3c",
      "content_free_signature": "[class]android.widget.TextView[resource_id]android:id/alertTitle"
    },
    {
      "package": "appinventor.ai_care_medisyshealthcare.Medisys",
      "visible": true,
      "checkable": false,
      "child_count": 0,
      "editable": false,
      "clickable": false,
      "is_password": false,
      "focusable": false,
      "enabled": true,
      "content_description": null,
      "children": [],
      "focused": false,
      "bounds": [
        [
          93,
          1116
        ],
        [
          1347,
          1144
        ]
      ],
      "resource_id": "android:id/titleDividerNoCustom",
      "checked": false,
      "text": null,
      "class": "android.view.View",
      "scrollable": false,
      "selected": false,
      "long_clickable": false,
      "parent": 4,
      "temp_id": 7,
      "size": "1254*28",
      "signature": "[class]android.view.View[resource_id]android:id/titleDividerNoCustom[text]None[enabled,,]",
      "view_str": "a10ae63483ff8af80fbab5dba7163f9e",
      "content_free_signature": "[class]android.view.View[resource_id]android:id/titleDividerNoCustom"
    },
    {
      "package": "appinventor.ai_care_medisyshealthcare.Medisys",
      "visible": true,
      "checkable": false,
      "child_count": 1,
      "editable": false,
      "clickable": false,
      "is_password": false,
      "focusable": false,
      "enabled": true,
      "content_description": null,
      "children": [
        9
      ],
      "focused": false,
      "bounds": [
        [
          93,
          1144
        ],
        [
          1347,
          1312
        ]
      ],
      "resource_id": "android:id/contentPanel",
      "checked": false,
      "text": null,
      "class": "android.widget.FrameLayout",
      "scrollable": false,
      "selected": false,
      "long_clickable": false,
      "parent": 3,
      "temp_id": 8,
      "size": "1254*168",
      "signature": "[class]android.widget.FrameLayout[resource_id]android:id/contentPanel[text]None[enabled,,]",
      "view_str": "82f62ceb52237c5390f3a18d7b9de7b9",
      "content_free_signature": "[class]android.widget.FrameLayout[resource_id]android:id/contentPanel"
    },
    {
      "package": "appinventor.ai_care_medisyshealthcare.Medisys",
      "visible": true,
      "checkable": false,
      "child_count": 1,
      "editable": false,
      "clickable": false,
      "is_password": false,
      "focusable": false,
      "enabled": true,
      "content_description": null,
      "children": [
        10
      ],
      "focused": false,
      "bounds": [
        [
          93,
          1144
        ],
        [
          1347,
          1220
        ]
      ],
      "resource_id": "android:id/scrollView",
      "checked": false,
      "text": null,
      "class": "android.widget.ScrollView",
      "scrollable": false,
      "selected": false,
      "long_clickable": false,
      "parent": 8,
      "temp_id": 9,
      "size": "1254*76",
      "signature": "[class]android.widget.ScrollView[resource_id]android:id/scrollView[text]None[enabled,,]",
      "view_str": "bf5dba6653bc5b90bd16d1d402d93033",
      "content_free_signature": "[class]android.widget.ScrollView[resource_id]android:id/scrollView"
    },
    {
      "package": "appinventor.ai_care_medisyshealthcare.Medisys",
      "visible": true,
      "checkable": false,
      "child_count": 1,
      "editable": false,
      "clickable": false,
      "is_password": false,
      "focusable": false,
      "enabled": true,
      "content_description": null,
      "children": [
        11
      ],
      "focused": false,
      "bounds": [
        [
          93,
          1144
        ],
        [
          1347,
          1220
        ]
      ],
      "resource_id": null,
      "checked": false,
      "text": null,
      "class": "android.widget.LinearLayout",
      "scrollable": false,
      "selected": false,
      "long_clickable": false,
      "parent": 9,
      "temp_id": 10,
      "size": "1254*76",
      "signature": "[class]android.widget.LinearLayout[resource_id]None[text]None[enabled,,]",
      "view_str": "304eefffa1e566ca65253961e1f37c4e",
      "content_free_signature": "[class]android.widget.LinearLayout[resource_id]None"
    },
    {
      "package": "appinventor.ai_care_medisyshealthcare.Medisys",
      "visible": true,
      "checkable": false,
      "child_count": 0,
      "editable": false,
      "clickable": false,
      "is_password": false,
      "focusable": false,
      "enabled": true,
      "content_description": null,
      "children": [],
      "focused": false,
      "bounds": [
        [
          93,
          1144
        ],
        [
          1347,
          1220
        ]
      ],
      "resource_id": "android:id/message",
      "checked": false,
      "text": "We would love to hear from you!",
      "class": "android.widget.TextView",
      "scrollable": false,
      "selected": false,
      "long_clickable": false,
      "parent": 10,
      "temp_id": 11,
      "size": "1254*76",
      "signature": "[class]android.widget.TextView[resource_id]android:id/message[text]We would love to hear from you![enabled,,]",
      "view_str": "e80d90e7ec34a0849c27b05ddc9d7358",
      "content_free_signature": "[class]android.widget.TextView[resource_id]android:id/message"
    },
    {
      "package": "appinventor.ai_care_medisyshealthcare.Medisys",
      "visible": true,
      "checkable": false,
      "child_count": 1,
      "editable": false,
      "clickable": false,
      "is_password": false,
      "focusable": true,
      "enabled": true,
      "content_description": null,
      "children": [
        13
      ],
      "focused": false,
      "bounds": [
        [
          93,
          1312
        ],
        [
          1347,
          1508
        ]
      ],
      "resource_id": "android:id/buttonPanel",
      "checked": false,
      "text": null,
      "class": "android.widget.ScrollView",
      "scrollable": false,
      "selected": false,
      "long_clickable": false,
      "parent": 3,
      "temp_id": 12,
      "size": "1254*196",
      "signature": "[class]android.widget.ScrollView[resource_id]android:id/buttonPanel[text]None[enabled,,]",
      "view_str": "595dc59b63325c0b13f3c647fa692c0e",
      "content_free_signature": "[class]android.widget.ScrollView[resource_id]android:id/buttonPanel"
    },
    {
      "package": "appinventor.ai_care_medisyshealthcare.Medisys",
      "visible": true,
      "checkable": false,
      "child_count": 3,
      "editable": false,
      "clickable": false,
      "is_password": false,
      "focusable": false,
      "enabled": true,
      "content_description": null,
      "children": [
        14,
        15,
        16
      ],
      "focused": false,
      "bounds": [
        [
          93,
          1312
        ],
        [
          1347,
          1508
        ]
      ],
      "resource_id": null,
      "checked": false,
      "text": null,
      "class": "android.widget.LinearLayout",
      "scrollable": false,
      "selected": false,
      "long_clickable": false,
      "parent": 12,
      "temp_id": 13,
      "size": "1254*196",
      "signature": "[class]android.widget.LinearLayout[resource_id]None[text]None[enabled,,]",
      "view_str": "5126aa8b79c8905fb257d27007296769",
      "content_free_signature": "[class]android.widget.LinearLayout[resource_id]None"
    },
    {
      "package": "appinventor.ai_care_medisyshealthcare.Medisys",
      "visible": true,
      "checkable": false,
      "child_count": 0,
      "editable": false,
      "clickable": true,
      "is_password": false,
      "focusable": true,
      "enabled": true,
      "content_description": null,
      "children": [],
      "focused": false,
      "bounds": [
        [
          135,
          1326
        ],
        [
          359,
          1494
        ]
      ],
      "resource_id": "android:id/button3",
      "checked": false,
      "text": "Exit",
      "class": "android.widget.Button",
      "scrollable": false,
      "selected": false,
      "long_clickable": false,
      "parent": 13,
      "temp_id": 14,
      "size": "224*168",
      "signature": "[class]android.widget.Button[resource_id]android:id/button3[text]Exit[enabled,,]",
      "view_str": "9e565d129c4b3cd0f00f819ab1d62a1f",
      "content_free_signature": "[class]android.widget.Button[resource_id]android:id/button3"
    },
    {
      "package": "appinventor.ai_care_medisyshealthcare.Medisys",
      "visible": true,
      "checkable": false,
      "child_count": 0,
      "editable": false,
      "clickable": true,
      "is_password": false,
      "focusable": true,
      "enabled": true,
      "content_description": null,
      "children": [],
      "focused": false,
      "bounds": [
        [
          819,
          1326
        ],
        [
          1053,
          1494
        ]
      ],
      "resource_id": "android:id/button2",
      "checked": false,
      "text": "Cancel",
      "class": "android.widget.Button",
      "scrollable": false,
      "selected": false,
      "long_clickable": false,
      "parent": 13,
      "temp_id": 15,
      "size": "234*168",
      "signature": "[class]android.widget.Button[resource_id]android:id/button2[text]Cancel[enabled,,]",
      "view_str": "c66e94cbca9b3d2c48c2b8c3814bf80f",
      "content_free_signature": "[class]android.widget.Button[resource_id]android:id/button2"
    },
    {
      "package": "appinventor.ai_care_medisyshealthcare.Medisys",
      "visible": true,
      "checkable": false,
      "child_count": 0,
      "editable": false,
      "clickable": true,
      "is_password": false,
      "focusable": true,
      "enabled": true,
      "content_description": null,
      "children": [],
      "focused": false,
      "bounds": [
        [
          1053,
          1326
        ],
        [
          1305,
          1494
        ]
      ],
      "resource_id": "android:id/button1",
      "checked": false,
      "text": "Rate Us",
      "class": "android.widget.Button",
      "scrollable": false,
      "selected": false,
      "long_clickable": false,
      "parent": 13,
      "temp_id": 16,
      "size": "252*168",
      "signature": "[class]android.widget.Button[resource_id]android:id/button1[text]Rate Us[enabled,,]",
      "view_str": "877962003d3f595bc4c19b080580bfa0",
      "content_free_signature": "[class]android.widget.Button[resource_id]android:id/button1"
    }
  ]
}